uoft_switchconfig/__init__.py
uoft_switchconfig/__main__.py
uoft_switchconfig/deploy.py
uoft_switchconfig/generate.py
uoft_switchconfig/types.py
uoft_switchconfig/util.py
uoft_switchconfig/example_template_dir/__init__.py
uoft_switchconfig/example_template_dir/comment-block-schema-example.j2
uoft_switchconfig/example_template_dir/data-model-example.j2
uoft_switchconfig-1.0.0.dist-info/METADATA
uoft_switchconfig-1.0.0.dist-info/WHEEL
uoft_switchconfig-1.0.0.dist-info/entry_points.txt
uoft_switchconfig-1.0.0.dist-info/RECORD
